cloudkv/__init__.py
cloudkv/__main__.py
cloudkv/_utils.py
cloudkv/async_client.py
cloudkv/py.typed
cloudkv/shared.py
cloudkv/sync_client.py
cloudkv-0.3.0.dist-info/METADATA
cloudkv-0.3.0.dist-info/WHEEL
cloudkv-0.3.0.dist-info/entry_points.txt
cloudkv-0.3.0.dist-info/licenses/LICENSE
cloudkv-0.3.0.dist-info/RECORD
